Financials/__init__.py
Financials/config/logging_config.py
Financials/config/spciq-api-financials-application.properties
Financials/constants/data_config.py
Financials/constants/functions_constants.py
Financials/constants/mnemonics_constants.py
Financials/constants/sdk_constants.py
Financials/services/financial_services_interface.py
Financials/services/helper/data_transform.py
Financials/services/impl/sdk_financial_services_impl.py
Financials/util/property_utils.py
financialstestdistribution-1.0.3.dist-info/METADATA
financialstestdistribution-1.0.3.dist-info/WHEEL
financialstestdistribution-1.0.3.dist-info/top_level.txt
financialstestdistribution-1.0.3.dist-info/RECORD
