Metadata-Version: 2.1
Name: financialstestdistribution
Version: 1.0.3
Summary: Module for financials pkg distribution test
Author-email: sp <sp@email.com>
Classifier: Programming Language :: Python :: 3
Classifier: License :: OSI Approved :: MIT License
Classifier: Operating System :: OS Independent
Requires-Dist: requests
Requires-Dist: pandas
Requires-Dist: IPython
